[
  {
    "url": "https://www.antigravity-portal.com/blog/202603/20260305_pachinko_beginners_guide/",
    "title": "📖 【完全ガイド】パチンコ初心者が知っておくべき基礎知識まとめ",
    "source": "blog",
    "postedAt": "2026-03-05T17:40:03.797Z"
  },
  {
    "url": "https://www.antigravity-portal.com/blog/202602/20260222_uber_weekly_summary_w2/",
    "title": "📊 週間総括：¥110,186達成！2週目は10万円の壁突破（2026年2月16日〜22日）",
    "source": "blog",
    "postedAt": "2026-03-05T17:40:06.978Z"
  },
  {
    "url": "https://www.antigravity-portal.com/blog/202602/20260222_uber_sunday_climax/",
    "title": "🎉 日曜日のフィナーレ：プロモ¥11,760で23,043円！週間10万超え達成（2026年2月22日）",
    "source": "blog",
    "postedAt": "2026-03-05T17:40:10.126Z"
  },
  {
    "url": "https://www.antigravity-portal.com/blog/202602/20260221_uber_saturday_weekend/",
    "title": "🔥 土曜日のフル稼働：30件達成で18,285円＋チップ付き（2026年2月21日）",
    "source": "blog",
    "postedAt": "2026-03-05T17:40:13.286Z"
  },
  {
    "url": "https://www.antigravity-portal.com/blog/202602/20260220_uber_friday_midweek/",
    "title": "📉 金曜日の堅実キープ：24件配達で13,928円、週末へ温存（2026年2月20日）",
    "source": "blog",
    "postedAt": "2026-03-05T17:40:16.517Z"
  }
]
